LICENSE
MANIFEST.in
README.md
install_script.py
main.py
setup.py
kdLaunchPad/__init__.py
kdLaunchPad/exception_handler.py
kdLaunchPad/fileutil.py
kdLaunchPad/kdLaunchPad.py
kdLaunchPad/kdLaunchPad.ui
kdLaunchPad/kdconfig.py
kdLaunchPad/kdconfigutil.py
kdLaunchPad/launchSession.py
kdLaunchPad/launchSession.ui
kdLaunchPad/sessionItem.py
kdLaunchPad/sessionItem.ui
kdLaunchPad.egg-info/PKG-INFO
kdLaunchPad.egg-info/SOURCES.txt
kdLaunchPad.egg-info/dependency_links.txt
kdLaunchPad.egg-info/entry_points.txt
kdLaunchPad.egg-info/not-zip-safe
kdLaunchPad.egg-info/requires.txt
kdLaunchPad.egg-info/top_level.txt
kdLaunchPad/image/background.jpg
kdLaunchPad/image/kdLaunchPad.ico