Metadata-Version: 1.2
Name: kdLaunchPad
Version: 1.0.8
Summary: auto run some programs after system start
Home-page: https://github.com/bkdwei/kdLaunchPad
Author: bkdwei
Author-email: bkdwei@163.com
Maintainer: 韦坤东
Maintainer-email: bkdwei@163.com
License: GPLv3+
Keywords: kdLaunchPad,autoStarter
Platform: any
Classifier: Development Status :: 5 - Production/Stable
Classifier: Environment :: X11 Applications :: Qt
Classifier: Intended Audience :: End Users/Desktop
Classifier: Natural Language :: Chinese (Simplified)
Classifier: Topic :: System :: Boot :: Init
Classifier: Programming Language :: Python :: 3
Classifier:  License :: OSI Approved :: GNU General Public License v3 or later (GPLv3+)
Classifier: Operating System :: OS Independent
Requires-Python: >=3.4
